<?xml version="1.0" encoding="utf-8" ?>

<Defs>

	<StatDef>
		<defName>Celsius_HeatCapacity</defName>
		<label>heat capacity</label>
		<description>How slowly the object changes its temperature.</description>
		<category>Basics</category>
		<workerClass>Celsius.StatWorker_HeatCapacity</workerClass>
		<hideAtValue>0</hideAtValue>
		<showOnPawns>false</showOnPawns>
		<showOnDefaultValue>false</showOnDefaultValue>
		<displayPriorityInCategory>1400</displayPriorityInCategory>
		<toStringStyle>FloatOne</toStringStyle>
		<formatString>{0}</formatString>
		<defaultBaseValue>0</defaultBaseValue>
		<minValue>0</minValue>
	</StatDef>

	<StatDef>
		<defName>Celsius_HeatConductivity</defName>
		<label>heat conductivity</label>
		<description>How much energy the object exchanges with surrounding air.</description>
		<category>Basics</category>
		<workerClass>Celsius.StatWorker_HeatConductivity</workerClass>
		<hideAtValue>0</hideAtValue>
		<showOnPawns>false</showOnPawns>
		<showOnDefaultValue>false</showOnDefaultValue>
		<displayPriorityInCategory>1398</displayPriorityInCategory>
		<toStringStyle>PercentZero</toStringStyle>
		<formatString>{0}</formatString>
		<minValue>0</minValue>
	</StatDef>

	<StatDef>
		<defName>Celsius_IgnitionTemperature</defName>
		<label>autoignition temperature</label>
		<description>Minimum temperature when this thing ignites.</description>
		<category>BasicsNonPawn</category>
		<hideAtValue>0</hideAtValue>
		<showOnPawns>false</showOnPawns>
		<showOnDefaultValue>false</showOnDefaultValue>
		<displayPriorityInCategory>2990</displayPriorityInCategory>
		<toStringStyle>Temperature</toStringStyle>
		<minifiedThingInherits>true</minifiedThingInherits>
		<defaultBaseValue>0</defaultBaseValue>
		<minValue>0</minValue>
	</StatDef>

</Defs>
